basketix/__init__.py
basketix/entities/__init__.py
basketix/entities/basketix_date.py
basketix/entities/basketix_error.py
basketix/entities/basketix_season.py
basketix/entities/basketix_week.py
basketix/entities/game_id.py
basketix/entities/injury.py
basketix/entities/language.py
basketix/entities/league_status.py
basketix/entities/nba_player_motions.py
basketix/entities/ranking_type.py
basketix/entities/transactions.py
basketix/exceptions/__init__.py
basketix/exceptions/unknown_nba_team.py
basketix/handlers/__init__.py
basketix/handlers/basketball_court.py
basketix/handlers/basketix_seasons.py
basketix/handlers/basketix_weeks.py
basketix/handlers/nba_games.py
basketix/handlers/nba_teams.py
basketix/helpers/__init__.py
basketix/helpers/aws.py
basketix/helpers/date_helper.py
basketix/helpers/helpers.py
basketix/models/__init__.py
basketix/models/attributes/__init__.py
basketix/models/attributes/basket_reference_id.py
basketix/models/attributes/basketix_id.py
basketix/models/attributes/basketix_team_id.py
basketix/models/attributes/game_id.py
basketix/models/attributes/nba_team_id.py
basketix/models/attributes/player_id.py
basketix/models/attributes/positions.py
basketix/models/attributes/season_id.py
basketix/models/attributes/week_id.py
basketix/models/basketball_court_settings.py
basketix/models/basketix_teams_model.py
basketix/models/nba_game_extended_status.py
basketix/models/nba_game_location.py
basketix/models/nba_game_status.py
basketix/models/nba_games.py
basketix/models/nba_players.py
basketix/models/nba_players_performances.py
basketix/tables/__init__.py
basketix/tables/basketix_dates.py
basketix/tables/basketix_free_agencies.py
basketix/tables/basketix_leagues.py
basketix/tables/basketix_seasons.py
basketix/tables/basketix_teams.py
basketix/tables/basketix_tokens.py
basketix/tables/basketix_user.py
basketix/tables/basketix_user_temp.py
basketix/tables/basketix_weeks.py
basketix/tables/dynamodb_table.py
basketix/tables/nba_games.py
basketix-0.27.0.dist-info/METADATA
basketix-0.27.0.dist-info/WHEEL
basketix-0.27.0.dist-info/RECORD
