Metadata-Version: 2.1
Name: basketix
Version: 0.27.0
Summary: 
Author: tlartigau
Author-email: thomas.lartigau@atinternet.com
Requires-Python: >=3.8,<4.0
Classifier: Programming Language :: Python :: 3
Classifier: Programming Language :: Python :: 3.8
Classifier: Programming Language :: Python :: 3.9
Classifier: Programming Language :: Python :: 3.10
Classifier: Programming Language :: Python :: 3.11
Requires-Dist: boto3 (>=1.26.69,<2.0.0)
Requires-Dist: isoweek (>=1.3.3,<2.0.0)
Requires-Dist: python-dateutil (>=2.8.2,<3.0.0)
Requires-Dist: pytz
Requires-Dist: typing-extensions (>=4.4.0,<5.0.0)
